{
  "classes": [
    {
      "id": 1,
      "name": "Druid",
      "hitDice": 8,
      "savingThrows": ["WIS", "INT"],
      "proficiencies": {
        "skills": [
          [
            "Arcana",
            "Animal Handling",
            "Insight",
            "Medicine",
            "Nature",
            "Perception",
            "Religion",
            "Survival"
          ],
          [
            "Arcana",
            "Animal Handling",
            "Insight",
            "Medicine",
            "Nature",
            "Perception",
            "Religion",
            "Survival"
          ]
        ]
      },
      "languages": ["Druidic"],
      "spellcasting": {
        "modifier": "WIS",
        "DC bonus": 8
      }
    }
  ]
}
